{
	"configurations" : 
	[
		{
			"directories" : 
			[
				{
					"build" : ".",
					"jsonFile" : "directory-.-Debug-f5ebdc15457944623624.json",
					"minimumCMakeVersion" : 
					{
						"string" : "3.15"
					},
					"projectIndex" : 0,
					"source" : ".",
					"targetIndexes" : 
					[
						0,
						1,
						2,
						3,
						4,
						5
					]
				}
			],
			"name" : "Debug",
			"projects" : 
			[
				{
					"directoryIndexes" : 
					[
						0
					],
					"name" : "pdv_lab07",
					"targetIndexes" : 
					[
						0,
						1,
						2,
						3,
						4,
						5
					]
				}
			],
			"targets" : 
			[
				{
					"directoryIndex" : 0,
					"id" : "07_0test_simd_support::@6890427a1f51a3e7e1df",
					"jsonFile" : "target-07_0test_simd_support-Debug-2545c1081bce76de1bb8.json",
					"name" : "07_0test_simd_support",
					"projectIndex" : 0
				},
				{
					"directoryIndex" : 0,
					"id" : "07_1autovectorization::@6890427a1f51a3e7e1df",
					"jsonFile" : "target-07_1autovectorization-Debug-03a9373e5aa8a829fa4e.json",
					"name" : "07_1autovectorization",
					"projectIndex" : 0
				},
				{
					"directoryIndex" : 0,
					"id" : "07_2intrinsics_test::@6890427a1f51a3e7e1df",
					"jsonFile" : "target-07_2intrinsics_test-Debug-3e3b84da223703842528.json",
					"name" : "07_2intrinsics_test",
					"projectIndex" : 0
				},
				{
					"directoryIndex" : 0,
					"id" : "07_3normal_distribution::@6890427a1f51a3e7e1df",
					"jsonFile" : "target-07_3normal_distribution-Debug-077a3e87529a09aff45c.json",
					"name" : "07_3normal_distribution",
					"projectIndex" : 0
				},
				{
					"directoryIndex" : 0,
					"id" : "07_4conditional_swap::@6890427a1f51a3e7e1df",
					"jsonFile" : "target-07_4conditional_swap-Debug-dc79306276a130ef530b.json",
					"name" : "07_4conditional_swap",
					"projectIndex" : 0
				},
				{
					"directoryIndex" : 0,
					"id" : "07_5matrix::@6890427a1f51a3e7e1df",
					"jsonFile" : "target-07_5matrix-Debug-289273c11ad8a1b5d933.json",
					"name" : "07_5matrix",
					"projectIndex" : 0
				}
			]
		}
	],
	"kind" : "codemodel",
	"paths" : 
	{
		"build" : "/home/kolesiko/sem4/PDV/week07/cmake-build-debug",
		"source" : "/home/kolesiko/sem4/PDV/week07"
	},
	"version" : 
	{
		"major" : 2,
		"minor" : 7
	}
}
